example_project/__init__.py
example_project/celery.py
example_project/requirements.txt
example_project/settings.py
example_project/urls.py
example_project/wsgi.py
swiftwind/__init__.py
swiftwind/defaults.py
swiftwind/urls.py
swiftwind/accounts/__init__.py
swiftwind/accounts/admin.py
swiftwind/accounts/models.py
swiftwind/accounts/tests.py
swiftwind/accounts/views.py
swiftwind/accounts/migrations/__init__.py
swiftwind/accounts/templates/hordak/accounts/account_create.html
swiftwind/accounts/templates/hordak/accounts/account_list.html
swiftwind/accounts/templates/hordak/accounts/account_transactions.html
swiftwind/accounts/templates/hordak/accounts/account_update.html
swiftwind/bank_imports/__init__.py
swiftwind/bank_imports/admin.py
swiftwind/bank_imports/models.py
swiftwind/bank_imports/tests.py
swiftwind/bank_imports/views.py
swiftwind/bank_imports/migrations/__init__.py
swiftwind/bank_rules/__init__.py
swiftwind/bank_rules/admin.py
swiftwind/bank_rules/models.py
swiftwind/bank_rules/tests.py
swiftwind/bank_rules/views.py
swiftwind/bank_rules/migrations/__init__.py
swiftwind/bank_transactions/__init__.py
swiftwind/bank_transactions/models.py
swiftwind/bank_transactions/tests.py
swiftwind/bank_transactions/views.py
swiftwind/bank_transactions/migrations/__init__.py
swiftwind/billing_cycle/__init__.py
swiftwind/billing_cycle/admin.py
swiftwind/billing_cycle/apps.py
swiftwind/billing_cycle/cycles.py
swiftwind/billing_cycle/exceptions.py
swiftwind/billing_cycle/models.py
swiftwind/billing_cycle/tasks.py
swiftwind/billing_cycle/tests.py
swiftwind/billing_cycle/views.py
swiftwind/billing_cycle/management/__init__.py
swiftwind/billing_cycle/management/commands/__init__.py
swiftwind/billing_cycle/management/commands/populate_billing_cycles.py
swiftwind/billing_cycle/migrations/0001_initial.py
swiftwind/billing_cycle/migrations/0002_check_non_overlapping.py
swiftwind/billing_cycle/migrations/0003_check_adjacent.py
swiftwind-0.2.0.dist-info/DESCRIPTION.rst
swiftwind-0.2.0.dist-info/METADATA
swiftwind-0.2.0.dist-info/RECORD
swiftwind-0.2.0.dist-info/WHEEL
swiftwind-0.2.0.dist-info/metadata.json
swiftwind-0.2.0.dist-info/top_level.txt
