Metadata-Version: 2.0
Name: swiftwind
Version: 0.2.0
Summary: User-friendly billing for communal households
Home-page: https://github.com/adamcharnock/swiftwind
Author: Adam Charnock
Author-email: adam@adamcharnock.com
License: MIT
Platform: UNKNOWN
Requires-Dist: celery (==4.0.2)
Requires-Dist: dj-database-url
Requires-Dist: dj-static
Requires-Dist: django (>=1.8)
Requires-Dist: django-adminlte2 (>=0.1.5)
Requires-Dist: django-bootstrap3 (<8,>=7)
Requires-Dist: django-celery-beat (==1.0.1)
Requires-Dist: django-extensions
Requires-Dist: django-hordak (>=1.4.0)
Requires-Dist: django-model-utils (>=2.5.0)
Requires-Dist: gunicorn
Requires-Dist: kombu (==4.0.2)
Requires-Dist: path.py
Requires-Dist: psycopg2
Requires-Dist: python-dateutil
Requires-Dist: redis (==2.10.5)
Requires-Dist: six
